visualdiscrimination/__init__.py
visualdiscrimination/__main__.py
visualdiscrimination/dialog.py
visualdiscrimination/whisker_visualdiscrimination.py
visualdiscriminationtask-0.1.4.dist-info/DESCRIPTION.rst
visualdiscriminationtask-0.1.4.dist-info/METADATA
visualdiscriminationtask-0.1.4.dist-info/RECORD
visualdiscriminationtask-0.1.4.dist-info/WHEEL
visualdiscriminationtask-0.1.4.dist-info/entry_points.txt
visualdiscriminationtask-0.1.4.dist-info/metadata.json
visualdiscriminationtask-0.1.4.dist-info/top_level.txt
